yogit/__init__.py
yogit/api/__init__.py
yogit/api/client.py
yogit/api/queries.py
yogit/api/statement.py
yogit/api/statements.py
yogit/storage/__init__.py
yogit/storage/storage.py
yogit/utils/__init__.py
yogit/utils/dateutils.py
yogit/yogit/__init__.py
yogit/yogit/account.py
yogit/yogit/branch.py
yogit/yogit/checks.py
yogit/yogit/cli.py
yogit/yogit/errors.py
yogit/yogit/logger.py
yogit/yogit/pullrequest.py
yogit/yogit/review.py
yogit/yogit/scrum.py
yogit/yogit/scrum_report.py
yogit/yogit/settings.py
yogit-1.0.0.dist-info/LICENSE
yogit-1.0.0.dist-info/METADATA
yogit-1.0.0.dist-info/WHEEL
yogit-1.0.0.dist-info/entry_points.txt
yogit-1.0.0.dist-info/top_level.txt
yogit-1.0.0.dist-info/zip-safe
yogit-1.0.0.dist-info/RECORD
