Metadata-Version: 2.1
Name: yogit
Version: 1.0.0
Summary: Command line utility for GitHub daily work.
Home-page: https://github.com/hasboeuf/yogit
Author: Adrien Gavignet
Author-email: adrien.gavignet@gmail.com
License: MIT
Keywords: git github utility branch pull requests
Platform: UNKNOWN
Classifier: Programming Language :: Python :: 3
Classifier: Operating System :: OS Independent
Requires-Dist: click
Requires-Dist: tabulate
Requires-Dist: requests
Requires-Dist: requests-toolbelt
Requires-Dist: PyYAML
Requires-Dist: pyperclip
